{
  "hash": "1e02a84c",
  "configHash": "811f62de",
  "lockfileHash": "c207118b",
  "browserHash": "c8b91cc8",
  "optimized": {
    "react": {
      "src": "../../node_modules/react/index.js",
      "file": "react.js",
      "fileHash": "2404c0ec",
      "needsInterop": true
    },
    "react-dom/client": {
      "src": "../../node_modules/react-dom/client.js",
      "file": "react-dom_client.js",
      "fileHash": "cb7dbc97",
      "needsInterop": true
    },
    "axios": {
      "src": "../../node_modules/axios/index.js",
      "file": "axios.js",
      "fileHash": "4d51c0e0",
      "needsInterop": false
    },
    "react-router-dom": {
      "src": "../../node_modules/react-router-dom/dist/index.mjs",
      "file": "react-router-dom.js",
      "fileHash": "f5d3c897",
      "needsInterop": false
    }
  },
  "chunks": {
    "chunk-5HNGYYSW": {
      "file": "chunk-5HNGYYSW.js"
    },
    "chunk-TVFQMRVC": {
      "file": "chunk-TVFQMRVC.js"
    },
    "chunk-G3PMV62Z": {
      "file": "chunk-G3PMV62Z.js"
    }
  }
}